README.rst
setup.py
banyan/__init__.py
banyan/_common_base.py
banyan/_dbg.hpp
banyan/_dict.py
banyan/_dummy_key.py
banyan/_frozen_dict.py
banyan/_frozen_set.py
banyan/_min_gap_updator.py
banyan/_node.py
banyan/_overlapping_intervals_updator.py
banyan/_rank_updator.py
banyan/_set.py
banyan/_trace.py
banyan/_views.py
banyan/dict_tree.cpp
banyan/dict_tree.hpp
banyan/frozen_dict_tree.cpp
banyan/frozen_dict_tree.hpp
banyan/frozen_set_tree.cpp
banyan/frozen_set_tree.hpp
banyan/min_gap_metadata.cpp
banyan/min_gap_metadata.hpp
banyan/module.cpp
banyan/node.cpp
banyan/node.hpp
banyan/overlapping_intervals_metadata.cpp
banyan/overlapping_intervals_metadata.hpp
banyan/rank_metadata.cpp
banyan/rank_metadata.hpp
banyan/set_tree.cpp
banyan/set_tree.hpp
banyan/tree.cpp
banyan/tree.hpp
banyan/tree_view.cpp
banyan/tree_view.hpp
banyan/_dsa/_binary_tree.hpp
banyan/_dsa/_binary_tree_node.hpp
banyan/_dsa/_dbg.hpp
banyan/_dsa/_functional.hpp
banyan/_dsa/_key_extractor.hpp
banyan/_dsa/_min_gap_updator.hpp
banyan/_dsa/_node_based_binary_tree.hpp
banyan/_dsa/_ov_tree.hpp
banyan/_dsa/_rank_updator.hpp
banyan/_dsa/_red_black_tree.hpp
banyan/_dsa/_red_black_tree_node.hpp
banyan/_dsa/_splay_tree.hpp
banyan/_int_imp/_build_tree_imp.cpp
banyan/_int_imp/_build_tree_imp.hpp
banyan/_int_imp/_dbg.hpp
banyan/_int_imp/_dict_tree_imp.hpp
banyan/_int_imp/_pymem_malloc_allocator.hpp
banyan/_int_imp/_pyobject_utils.cpp
banyan/_int_imp/_pyobject_utils.hpp
banyan/_int_imp/_set_tree_imp.hpp
banyan/_int_imp/_tree_imp.hpp
banyan/_int_imp/_tree_imp_alg_base.hpp
banyan/_int_imp/_tree_imp_cb_metadata_base.hpp
banyan/_int_imp/_tree_imp_interval_max_metadata_base.hpp
banyan/_int_imp/_tree_imp_lt_base.hpp
banyan/_int_imp/_tree_imp_mapping_base.hpp
banyan/_int_imp/_tree_imp_metadata_base.hpp
banyan/_int_imp/_tree_imp_min_gap_metadata_base.hpp
banyan/_int_imp/_tree_imp_non_pyobject_key_value_type_dict_base.hpp
banyan/_int_imp/_tree_imp_non_pyobject_key_value_type_set_base.hpp
pyannote_banyan.egg-info/PKG-INFO
pyannote_banyan.egg-info/SOURCES.txt
pyannote_banyan.egg-info/dependency_links.txt
pyannote_banyan.egg-info/top_level.txt