Metadata-Version: 1.1
Name: pyannote-banyan
Version: 0.1.6
Summary: Highly-optimized search trees (red-black, splay, and sorted-list) with optional augmentation (dynamic order statistics, interval trees, etc.)
Home-page: https://github.com/pyannote/pyannote-banyan
Author: Herve Bredin
Author-email: bredin at limsi.fr
License: BSD
Platform: UNKNOWN
Classifier: Development Status :: 4 - Beta
Classifier: Intended Audience :: Developers
Classifier: License :: OSI Approved :: BSD License
Classifier: Operating System :: OS Independent
Classifier: Programming Language :: Python
Classifier: Programming Language :: Python :: 2
Classifier: Programming Language :: Python :: 3
Classifier: Programming Language :: C++
Classifier: Topic :: Software Development :: Libraries :: Python Modules
Requires: UnittestRandGenState
